{"data_type": "mice", "data_folder": "./ext_data/Rosenberg2021/", "data_path_type": "auto", "comb_type": "", "var_name": ["gamma", "c_alph", "a_alph", "c_lam", "a_lam", "temp", "a_w0"], "kwargs": {"x0": [0.5, 0.1, 0.1, 0.5, 0.5, 0.5, 0.0], "bounds": [[0.0, 0.999], [0.001, 0.5], [0.001, 0.5], [0.0, 0.999], [0.0, 0.999], [0.001, 1.0], [-100, 100]], "opt_method": "Nelder-Mead"}, "alg_type": "hnac-gn-gv-goi", "level": 1, "save_name": "mle_hnac-gn-gv-goi-l1-mice", "verbose": true, "save_path": "MLE_results/Fits/SingleRun/mle_hnac-gn-gv-goi-mice_Nelder-Mead"}